{"h": [{"id": "366023", "minute": "5", "result": "BlockedShot", "X": "0.7369999694824219", "Y": "0.355", "xG": "0.016189781948924065", "player": "Musa Barrow", "h_a": "h", "player_id": "6512", "situation": "OpenPlay", "season": "2019", "shotType": "RightFoot", "match_id": "13350", "h_team": "Bologna", "a_team": "Juventus", "h_goals": "0", "a_goals": "2", "date": "2020-06-22 19:45:00", "player_assisted": "Nicola Sansone", "lastAction": "Pass"}, {"id": "366026", "minute": "8", "result": "BlockedShot", "X": "0.730999984741211", "Y": "0.49599998474121093", "xG": "0.021129358559846878", "player": "Nicola Sansone", "h_a": "h", "player_id": "1826", "situation": "OpenPlay", "season": "2019", "shotType": "RightFoot", "match_id": "13350", "h_team": "Bologna", "a_team": "Juventus", "h_goals": "0", "a_goals": "2", "date": "2020-06-22 19:45:00", "player_assisted": "Gary Medel", "lastAction": "Pass"}, {"id": "366027", "minute": "8", "result": "BlockedShot", "X": "0.7290000152587891", "Y": "0.5520000076293945", "xG": "0.016730573028326035", "player": "Mattias Svanberg", "h_a": "h", "player_id": "6974", "situation": "OpenPlay", "season": "2019", "shotType": "RightFoot", "match_id": "13350", "h_team": "Bologna", "a_team": "Juventus", "h_goals": "0", "a_goals": "2", "date": "2020-06-22 19:45:00", "player_assisted": "Gary Medel", "lastAction": "Pass"}, {"id": "366028", "minute": "12", "result": "BlockedShot", "X": "0.7630000305175781", "Y": "0.7030000305175781", "xG": "0.01260661706328392", "player": "Mattias Svanberg", "h_a": "h", "player_id": "6974", "situation": "OpenPlay", "season": "2019", "shotType": "RightFoot", "match_id": "13350", "h_team": "Bologna", "a_team": "Juventus", "h_goals": "0", "a_goals": "2", "date": "2020-06-22 19:45:00", "player_assisted": null, "lastAction": "None"}, {"id": "366031", "minute": "33", "result": "MissedShots", "X": "0.9290000152587891", "Y": "0.67", "xG": "0.012349562719464302", "player": "Mattias Svanberg", "h_a": "h", "player_id": "6974", "situation": "FromCorner", "season": "2019", "shotType": "Head", "match_id": "13350", "h_team": "Bologna", "a_team": "Juventus", "h_goals": "0", "a_goals": "2", "date": "2020-06-22 19:45:00", "player_assisted": "Musa Barrow", "lastAction": "Aerial"}, {"id": "366032", "minute": "35", "result": "SavedShot", "X": "0.7169999694824218", "Y": "0.5429999923706055", "xG": "0.013517986983060837", "player": "Gary Medel", "h_a": "h", "player_id": "1510", "situation": "OpenPlay", "season": "2019", "shotType": "RightFoot", "match_id": "13350", "h_team": "Bologna", "a_team": "Juventus", "h_goals": "0", "a_goals": "2", "date": "2020-06-22 19:45:00", "player_assisted": null, "lastAction": "Card"}, {"id": "366034", "minute": "37", "result": "MissedShots", "X": "0.735999984741211", "Y": "0.685", "xG": "0.012240855023264885", "player": "Nicola Sansone", "h_a": "h", "player_id": "1826", "situation": "OpenPlay", "season": "2019", "shotType": "RightFoot", "match_id": "13350", "h_team": "Bologna", "a_team": "Juventus", "h_goals": "0", "a_goals": "2", "date": "2020-06-22 19:45:00", "player_assisted": "Mitchell Dijks", "lastAction": "Pass"}, {"id": "366036", "minute": "44", "result": "BlockedShot", "X": "0.8280000305175781", "Y": "0.5670000076293945", "xG": "0.04275541007518768", "player": "Riccardo Orsolini", "h_a": "h", "player_id": "6160", "situation": "OpenPlay", "season": "2019", "shotType": "LeftFoot", "match_id": "13350", "h_team": "Bologna", "a_team": "Juventus", "h_goals": "0", "a_goals": "2", "date": "2020-06-22 19:45:00", "player_assisted": null, "lastAction": "None"}, {"id": "366037", "minute": "45", "result": "MissedShots", "X": "0.7519999694824219", "Y": "0.34200000762939453", "xG": "0.01805552840232849", "player": "Mattias Svanberg", "h_a": "h", "player_id": "6974", "situation": "OpenPlay", "season": "2019", "shotType": "RightFoot", "match_id": "13350", "h_team": "Bologna", "a_team": "Juventus", "h_goals": "0", "a_goals": "2", "date": "2020-06-22 19:45:00", "player_assisted": "Gary Medel", "lastAction": "Pass"}, {"id": "366038", "minute": "46", "result": "MissedShots", "X": "0.769000015258789", "Y": "0.49", "xG": "0.013935533352196217", "player": "Mattias Svanberg", "h_a": "h", "player_id": "6974", "situation": "OpenPlay", "season": "2019", "shotType": "RightFoot", "match_id": "13350", "h_team": "Bologna", "a_team": "Juventus", "h_goals": "0", "a_goals": "2", "date": "2020-06-22 19:45:00", "player_assisted": "Riccardo Orsolini", "lastAction": "Chipped"}, {"id": "366039", "minute": "49", "result": "BlockedShot", "X": "0.7669999694824219", "Y": "0.4779999923706055", "xG": "0.02248227410018444", "player": "Mattias Svanberg", "h_a": "h", "player_id": "6974", "situation": "OpenPlay", "season": "2019", "shotType": "RightFoot", "match_id": "13350", "h_team": "Bologna", "a_team": "Juventus", "h_goals": "0", "a_goals": "2", "date": "2020-06-22 19:45:00", "player_assisted": "Musa Barrow", "lastAction": "Pass"}, {"id": "366045", "minute": "58", "result": "BlockedShot", "X": "0.9330000305175781", "Y": "0.43900001525878907", "xG": "0.11923405528068542", "player": "Musa Barrow", "h_a": "h", "player_id": "6512", "situation": "FromCorner", "season": "2019", "shotType": "RightFoot", "match_id": "13350", "h_team": "Bologna", "a_team": "Juventus", "h_goals": "0", "a_goals": "2", "date": "2020-06-22 19:45:00", "player_assisted": "Rodrigo Palacio", "lastAction": "HeadPass"}, {"id": "366046", "minute": "60", "result": "MissedShots", "X": "0.8019999694824219", "Y": "0.49599998474121093", "xG": "0.04117628186941147", "player": "Riccardo Orsolini", "h_a": "h", "player_id": "6160", "situation": "FromCorner", "season": "2019", "shotType": "LeftFoot", "match_id": "13350", "h_team": "Bologna", "a_team": "Juventus", "h_goals": "0", "a_goals": "2", "date": "2020-06-22 19:45:00", "player_assisted": "Roberto Soriano", "lastAction": "TakeOn"}, {"id": "366048", "minute": "63", "result": "BlockedShot", "X": "0.895", "Y": "0.6659999847412109", "xG": "0.027335049584507942", "player": "Danilo", "h_a": "h", "player_id": "1140", "situation": "FromCorner", "season": "2019", "shotType": "Head", "match_id": "13350", "h_team": "Bologna", "a_team": "Juventus", "h_goals": "0", "a_goals": "2", "date": "2020-06-22 19:45:00", "player_assisted": null, "lastAction": "None"}, {"id": "366049", "minute": "66", "result": "BlockedShot", "X": "0.8530000305175781", "Y": "0.455", "xG": "0.06512333452701569", "player": "Musa Barrow", "h_a": "h", "player_id": "6512", "situation": "SetPiece", "season": "2019", "shotType": "RightFoot", "match_id": "13350", "h_team": "Bologna", "a_team": "Juventus", "h_goals": "0", "a_goals": "2", "date": "2020-06-22 19:45:00", "player_assisted": null, "lastAction": "None"}, {"id": "366052", "minute": "76", "result": "BlockedShot", "X": "0.735", "Y": "0.48700000762939455", "xG": "0.015485634095966816", "player": "Nicol\u00e1s Dom\u00ednguez", "h_a": "h", "player_id": "8252", "situation": "OpenPlay", "season": "2019", "shotType": "RightFoot", "match_id": "13350", "h_team": "Bologna", "a_team": "Juventus", "h_goals": "0", "a_goals": "2", "date": "2020-06-22 19:45:00", "player_assisted": "Rodrigo Palacio", "lastAction": "Pass"}, {"id": "366053", "minute": "79", "result": "MissedShots", "X": "0.725", "Y": "0.3270000076293945", "xG": "0.011297879740595818", "player": "Riccardo Orsolini", "h_a": "h", "player_id": "6160", "situation": "OpenPlay", "season": "2019", "shotType": "LeftFoot", "match_id": "13350", "h_team": "Bologna", "a_team": "Juventus", "h_goals": "0", "a_goals": "2", "date": "2020-06-22 19:45:00", "player_assisted": "Rodrigo Palacio", "lastAction": "Pass"}, {"id": "366054", "minute": "92", "result": "BlockedShot", "X": "0.850999984741211", "Y": "0.5670000076293945", "xG": "0.009447417221963406", "player": "Takehiro Tomiyasu", "h_a": "h", "player_id": "7931", "situation": "SetPiece", "season": "2019", "shotType": "Head", "match_id": "13350", "h_team": "Bologna", "a_team": "Juventus", "h_goals": "0", "a_goals": "2", "date": "2020-06-22 19:45:00", "player_assisted": "Musa Juwara", "lastAction": "Aerial"}, {"id": "366055", "minute": "94", "result": "BlockedShot", "X": "0.7769999694824219", "Y": "0.6359999847412109", "xG": "0.07050769776105881", "player": "Musa Barrow", "h_a": "h", "player_id": "6512", "situation": "DirectFreekick", "season": "2019", "shotType": "RightFoot", "match_id": "13350", "h_team": "Bologna", "a_team": "Juventus", "h_goals": "0", "a_goals": "2", "date": "2020-06-22 19:45:00", "player_assisted": null, "lastAction": "Standard"}, {"id": "366056", "minute": "94", "result": "BlockedShot", "X": "0.7619999694824219", "Y": "0.4640000152587891", "xG": "0.017142076045274734", "player": "Takehiro Tomiyasu", "h_a": "h", "player_id": "7931", "situation": "SetPiece", "season": "2019", "shotType": "LeftFoot", "match_id": "13350", "h_team": "Bologna", "a_team": "Juventus", "h_goals": "0", "a_goals": "2", "date": "2020-06-22 19:45:00", "player_assisted": null, "lastAction": "Rebound"}], "a": [{"id": "366024", "minute": "6", "result": "SavedShot", "X": "0.8490000152587891", "Y": "0.6609999847412109", "xG": "0.060610588639974594", "player": "Cristiano Ronaldo", "h_a": "a", "player_id": "2371", "situation": "OpenPlay", "season": "2019", "shotType": "RightFoot", "match_id": "13350", "h_team": "Bologna", "a_team": "Juventus", "h_goals": "0", "a_goals": "2", "date": "2020-06-22 19:45:00", "player_assisted": "Federico Bernardeschi", "lastAction": "TakeOn"}, {"id": "366025", "minute": "6", "result": "MissedShots", "X": "0.8719999694824219", "Y": "0.31", "xG": "0.032585397362709045", "player": "Paulo Dybala", "h_a": "a", "player_id": "1294", "situation": "OpenPlay", "season": "2019", "shotType": "LeftFoot", "match_id": "13350", "h_team": "Bologna", "a_team": "Juventus", "h_goals": "0", "a_goals": "2", "date": "2020-06-22 19:45:00", "player_assisted": "Federico Bernardeschi", "lastAction": "BallRecovery"}, {"id": "366029", "minute": "16", "result": "MissedShots", "X": "0.779000015258789", "Y": "0.7759999847412109", "xG": "0.040526263415813446", "player": "Cristiano Ronaldo", "h_a": "a", "player_id": "2371", "situation": "DirectFreekick", "season": "2019", "shotType": "RightFoot", "match_id": "13350", "h_team": "Bologna", "a_team": "Juventus", "h_goals": "0", "a_goals": "2", "date": "2020-06-22 19:45:00", "player_assisted": null, "lastAction": "Standard"}, {"id": "366030", "minute": "22", "result": "Goal", "X": "0.885", "Y": "0.5", "xG": "0.7612589001655579", "player": "Cristiano Ronaldo", "h_a": "a", "player_id": "2371", "situation": "Penalty", "season": "2019", "shotType": "RightFoot", "match_id": "13350", "h_team": "Bologna", "a_team": "Juventus", "h_goals": "0", "a_goals": "2", "date": "2020-06-22 19:45:00", "player_assisted": null, "lastAction": "Standard"}, {"id": "366033", "minute": "35", "result": "Goal", "X": "0.805", "Y": "0.47900001525878905", "xG": "0.0656103789806366", "player": "Paulo Dybala", "h_a": "a", "player_id": "1294", "situation": "OpenPlay", "season": "2019", "shotType": "LeftFoot", "match_id": "13350", "h_team": "Bologna", "a_team": "Juventus", "h_goals": "0", "a_goals": "2", "date": "2020-06-22 19:45:00", "player_assisted": "Federico Bernardeschi", "lastAction": "Pass"}, {"id": "366035", "minute": "39", "result": "MissedShots", "X": "0.9390000152587891", "Y": "0.34599998474121096", "xG": "0.25065580010414124", "player": "Paulo Dybala", "h_a": "a", "player_id": "1294", "situation": "OpenPlay", "season": "2019", "shotType": "RightFoot", "match_id": "13350", "h_team": "Bologna", "a_team": "Juventus", "h_goals": "0", "a_goals": "2", "date": "2020-06-22 19:45:00", "player_assisted": "Cristiano Ronaldo", "lastAction": "Cross"}, {"id": "366040", "minute": "51", "result": "MissedShots", "X": "0.8680000305175781", "Y": "0.664000015258789", "xG": "0.2145967036485672", "player": "Cristiano Ronaldo", "h_a": "a", "player_id": "2371", "situation": "OpenPlay", "season": "2019", "shotType": "RightFoot", "match_id": "13350", "h_team": "Bologna", "a_team": "Juventus", "h_goals": "0", "a_goals": "2", "date": "2020-06-22 19:45:00", "player_assisted": "Federico Bernardeschi", "lastAction": "Pass"}, {"id": "366041", "minute": "52", "result": "ShotOnPost", "X": "0.81", "Y": "0.31", "xG": "0.04242558777332306", "player": "Federico Bernardeschi", "h_a": "a", "player_id": "1424", "situation": "OpenPlay", "season": "2019", "shotType": "LeftFoot", "match_id": "13350", "h_team": "Bologna", "a_team": "Juventus", "h_goals": "0", "a_goals": "2", "date": "2020-06-22 19:45:00", "player_assisted": "Juan Cuadrado", "lastAction": "Pass"}, {"id": "366042", "minute": "53", "result": "BlockedShot", "X": "0.8119999694824219", "Y": "0.5879999923706055", "xG": "0.06632915139198303", "player": "Cristiano Ronaldo", "h_a": "a", "player_id": "2371", "situation": "OpenPlay", "season": "2019", "shotType": "LeftFoot", "match_id": "13350", "h_team": "Bologna", "a_team": "Juventus", "h_goals": "0", "a_goals": "2", "date": "2020-06-22 19:45:00", "player_assisted": "Rodrigo Bentancur", "lastAction": "Pass"}, {"id": "366043", "minute": "54", "result": "BlockedShot", "X": "0.775", "Y": "0.5540000152587891", "xG": "0.08584389835596085", "player": "Miralem Pjanic", "h_a": "a", "player_id": "1290", "situation": "DirectFreekick", "season": "2019", "shotType": "RightFoot", "match_id": "13350", "h_team": "Bologna", "a_team": "Juventus", "h_goals": "0", "a_goals": "2", "date": "2020-06-22 19:45:00", "player_assisted": null, "lastAction": "Standard"}, {"id": "366044", "minute": "54", "result": "MissedShots", "X": "0.799000015258789", "Y": "0.534000015258789", "xG": "0.04406140744686127", "player": "Paulo Dybala", "h_a": "a", "player_id": "1294", "situation": "OpenPlay", "season": "2019", "shotType": "RightFoot", "match_id": "13350", "h_team": "Bologna", "a_team": "Juventus", "h_goals": "0", "a_goals": "2", "date": "2020-06-22 19:45:00", "player_assisted": null, "lastAction": "None"}, {"id": "366047", "minute": "61", "result": "BlockedShot", "X": "0.7919999694824219", "Y": "0.3609999847412109", "xG": "0.04028118774294853", "player": "Federico Bernardeschi", "h_a": "a", "player_id": "1424", "situation": "OpenPlay", "season": "2019", "shotType": "LeftFoot", "match_id": "13350", "h_team": "Bologna", "a_team": "Juventus", "h_goals": "0", "a_goals": "2", "date": "2020-06-22 19:45:00", "player_assisted": "Paulo Dybala", "lastAction": "Pass"}, {"id": "366050", "minute": "70", "result": "MissedShots", "X": "0.7719999694824219", "Y": "0.4779999923706055", "xG": "0.05089826136827469", "player": "Federico Bernardeschi", "h_a": "a", "player_id": "1424", "situation": "OpenPlay", "season": "2019", "shotType": "LeftFoot", "match_id": "13350", "h_team": "Bologna", "a_team": "Juventus", "h_goals": "0", "a_goals": "2", "date": "2020-06-22 19:45:00", "player_assisted": "Aaron Ramsey", "lastAction": "Pass"}, {"id": "366051", "minute": "72", "result": "MissedShots", "X": "0.75", "Y": "0.5879999923706055", "xG": "0.03378545120358467", "player": "Cristiano Ronaldo", "h_a": "a", "player_id": "2371", "situation": "OpenPlay", "season": "2019", "shotType": "RightFoot", "match_id": "13350", "h_team": "Bologna", "a_team": "Juventus", "h_goals": "0", "a_goals": "2", "date": "2020-06-22 19:45:00", "player_assisted": "Blaise Matuidi", "lastAction": "Pass"}]}