{"h": [{"id": "184434", "minute": "8", "result": "SavedShot", "X": "0.8190000152587891", "Y": "0.4909999847412109", "xG": "0.06231393665075302", "player": "V\u00edctor Camarasa", "h_a": "h", "player_id": "2390", "situation": "OpenPlay", "season": "2017", "shotType": "RightFoot", "match_id": "8043", "h_team": "Real Betis", "a_team": "Athletic Club", "h_goals": "0", "a_goals": "2", "date": "2017-12-22 18:30:00", "player_assisted": null, "lastAction": "BallRecovery"}, {"id": "184435", "minute": "10", "result": "MissedShots", "X": "0.8", "Y": "0.7240000152587891", "xG": "0.018189074471592903", "player": "Cristian Tello", "h_a": "h", "player_id": "1421", "situation": "OpenPlay", "season": "2017", "shotType": "RightFoot", "match_id": "8043", "h_team": "Real Betis", "a_team": "Athletic Club", "h_goals": "0", "a_goals": "2", "date": "2017-12-22 18:30:00", "player_assisted": "Sergio Le\u00f3n", "lastAction": "Chipped"}, {"id": "184436", "minute": "15", "result": "SavedShot", "X": "0.9209999847412109", "Y": "0.8169999694824219", "xG": "0.07238271832466125", "player": "Joaqu\u00edn", "h_a": "h", "player_id": "2148", "situation": "DirectFreekick", "season": "2017", "shotType": "RightFoot", "match_id": "8043", "h_team": "Real Betis", "a_team": "Athletic Club", "h_goals": "0", "a_goals": "2", "date": "2017-12-22 18:30:00", "player_assisted": null, "lastAction": "Standard"}, {"id": "184437", "minute": "15", "result": "BlockedShot", "X": "0.8159999847412109", "Y": "0.45799999237060546", "xG": "0.05017293989658356", "player": "Fabi\u00e1n", "h_a": "h", "player_id": "2447", "situation": "SetPiece", "season": "2017", "shotType": "LeftFoot", "match_id": "8043", "h_team": "Real Betis", "a_team": "Athletic Club", "h_goals": "0", "a_goals": "2", "date": "2017-12-22 18:30:00", "player_assisted": "V\u00edctor Camarasa", "lastAction": "BallTouch"}, {"id": "184438", "minute": "15", "result": "SavedShot", "X": "0.730999984741211", "Y": "0.63", "xG": "0.012401099316775799", "player": "Cristian Tello", "h_a": "h", "player_id": "1421", "situation": "SetPiece", "season": "2017", "shotType": "RightFoot", "match_id": "8043", "h_team": "Real Betis", "a_team": "Athletic Club", "h_goals": "0", "a_goals": "2", "date": "2017-12-22 18:30:00", "player_assisted": null, "lastAction": "Rebound"}, {"id": "184439", "minute": "27", "result": "MissedShots", "X": "0.9519999694824218", "Y": "0.3240000152587891", "xG": "0.03428046777844429", "player": "V\u00edctor Camarasa", "h_a": "h", "player_id": "2390", "situation": "FromCorner", "season": "2017", "shotType": "RightFoot", "match_id": "8043", "h_team": "Real Betis", "a_team": "Athletic Club", "h_goals": "0", "a_goals": "2", "date": "2017-12-22 18:30:00", "player_assisted": "Joaqu\u00edn", "lastAction": "Cross"}, {"id": "184446", "minute": "39", "result": "MissedShots", "X": "0.7819999694824219", "Y": "0.69", "xG": "0.01733522303402424", "player": "Riza Durmisi", "h_a": "h", "player_id": "5036", "situation": "FromCorner", "season": "2017", "shotType": "LeftFoot", "match_id": "8043", "h_team": "Real Betis", "a_team": "Athletic Club", "h_goals": "0", "a_goals": "2", "date": "2017-12-22 18:30:00", "player_assisted": null, "lastAction": "None"}, {"id": "184448", "minute": "42", "result": "BlockedShot", "X": "0.7519999694824219", "Y": "0.47200000762939454", "xG": "0.0251590758562088", "player": "Sergio Le\u00f3n", "h_a": "h", "player_id": "5095", "situation": "OpenPlay", "season": "2017", "shotType": "LeftFoot", "match_id": "8043", "h_team": "Real Betis", "a_team": "Athletic Club", "h_goals": "0", "a_goals": "2", "date": "2017-12-22 18:30:00", "player_assisted": "Cristian Tello", "lastAction": "TakeOn"}, {"id": "184456", "minute": "56", "result": "BlockedShot", "X": "0.7680000305175781", "Y": "0.4129999923706055", "xG": "0.02801552414894104", "player": "Fabi\u00e1n", "h_a": "h", "player_id": "2447", "situation": "OpenPlay", "season": "2017", "shotType": "LeftFoot", "match_id": "8043", "h_team": "Real Betis", "a_team": "Athletic Club", "h_goals": "0", "a_goals": "2", "date": "2017-12-22 18:30:00", "player_assisted": "Cristian Tello", "lastAction": "Pass"}, {"id": "184458", "minute": "61", "result": "MissedShots", "X": "0.53", "Y": "0.855", "xG": "0.01735149882733822", "player": "Zouhair Feddal", "h_a": "h", "player_id": "2388", "situation": "DirectFreekick", "season": "2017", "shotType": "LeftFoot", "match_id": "8043", "h_team": "Real Betis", "a_team": "Athletic Club", "h_goals": "0", "a_goals": "2", "date": "2017-12-22 18:30:00", "player_assisted": null, "lastAction": "Standard"}, {"id": "184459", "minute": "62", "result": "SavedShot", "X": "0.8909999847412109", "Y": "0.675", "xG": "0.3397428095340729", "player": "Sergio Le\u00f3n", "h_a": "h", "player_id": "5095", "situation": "OpenPlay", "season": "2017", "shotType": "LeftFoot", "match_id": "8043", "h_team": "Real Betis", "a_team": "Athletic Club", "h_goals": "0", "a_goals": "2", "date": "2017-12-22 18:30:00", "player_assisted": "Joaqu\u00edn", "lastAction": "Throughball"}, {"id": "184460", "minute": "64", "result": "BlockedShot", "X": "0.8219999694824218", "Y": "0.24899999618530275", "xG": "0.02290717512369156", "player": "Cristian Tello", "h_a": "h", "player_id": "1421", "situation": "OpenPlay", "season": "2017", "shotType": "LeftFoot", "match_id": "8043", "h_team": "Real Betis", "a_team": "Athletic Club", "h_goals": "0", "a_goals": "2", "date": "2017-12-22 18:30:00", "player_assisted": "Fabi\u00e1n", "lastAction": "Pass"}, {"id": "184461", "minute": "72", "result": "MissedShots", "X": "0.965999984741211", "Y": "0.5629999923706055", "xG": "0.08036783337593079", "player": "Sergio Le\u00f3n", "h_a": "h", "player_id": "5095", "situation": "OpenPlay", "season": "2017", "shotType": "Head", "match_id": "8043", "h_team": "Real Betis", "a_team": "Athletic Club", "h_goals": "0", "a_goals": "2", "date": "2017-12-22 18:30:00", "player_assisted": null, "lastAction": "Aerial"}, {"id": "184464", "minute": "77", "result": "SavedShot", "X": "0.9080000305175782", "Y": "0.5429999923706055", "xG": "0.4631738066673279", "player": "Sergio Le\u00f3n", "h_a": "h", "player_id": "5095", "situation": "OpenPlay", "season": "2017", "shotType": "RightFoot", "match_id": "8043", "h_team": "Real Betis", "a_team": "Athletic Club", "h_goals": "0", "a_goals": "2", "date": "2017-12-22 18:30:00", "player_assisted": "Cristian Tello", "lastAction": "Pass"}, {"id": "184465", "minute": "82", "result": "SavedShot", "X": "0.715999984741211", "Y": "0.30700000762939456", "xG": "0.012264840304851532", "player": "Cristian Tello", "h_a": "h", "player_id": "1421", "situation": "FromCorner", "season": "2017", "shotType": "RightFoot", "match_id": "8043", "h_team": "Real Betis", "a_team": "Athletic Club", "h_goals": "0", "a_goals": "2", "date": "2017-12-22 18:30:00", "player_assisted": null, "lastAction": "None"}, {"id": "184466", "minute": "84", "result": "OwnGoal", "X": "0.030999999046325683", "Y": "0.6090000152587891", "xG": "0", "player": "Zouhair Feddal", "h_a": "h", "player_id": "2388", "situation": "OpenPlay", "season": "2017", "shotType": "Head", "match_id": "8043", "h_team": "Real Betis", "a_team": "Athletic Club", "h_goals": "0", "a_goals": "2", "date": "2017-12-22 18:30:00", "player_assisted": null, "lastAction": "None"}, {"id": "184467", "minute": "89", "result": "MissedShots", "X": "0.7580000305175781", "Y": "0.3039999961853027", "xG": "0.012050516903400421", "player": "Aissa Mandi", "h_a": "h", "player_id": "3237", "situation": "OpenPlay", "season": "2017", "shotType": "RightFoot", "match_id": "8043", "h_team": "Real Betis", "a_team": "Athletic Club", "h_goals": "0", "a_goals": "2", "date": "2017-12-22 18:30:00", "player_assisted": "Nahuel", "lastAction": "Pass"}], "a": [{"id": "184432", "minute": "6", "result": "BlockedShot", "X": "0.8519999694824218", "Y": "0.3579999923706055", "xG": "0.06357569992542267", "player": "Ra\u00fal Garc\u00eda", "h_a": "a", "player_id": "2400", "situation": "OpenPlay", "season": "2017", "shotType": "RightFoot", "match_id": "8043", "h_team": "Real Betis", "a_team": "Athletic Club", "h_goals": "0", "a_goals": "2", "date": "2017-12-22 18:30:00", "player_assisted": "De Marcos", "lastAction": "Pass"}, {"id": "184433", "minute": "6", "result": "MissedShots", "X": "0.850999984741211", "Y": "0.5720000076293945", "xG": "0.012693962082266808", "player": "Mikel Rico", "h_a": "a", "player_id": "2406", "situation": "FromCorner", "season": "2017", "shotType": "Head", "match_id": "8043", "h_team": "Real Betis", "a_team": "Athletic Club", "h_goals": "0", "a_goals": "2", "date": "2017-12-22 18:30:00", "player_assisted": "Markel Susaeta", "lastAction": "Aerial"}, {"id": "184440", "minute": "29", "result": "MissedShots", "X": "0.8569999694824219", "Y": "0.48700000762939455", "xG": "0.057423412799835205", "player": "Mikel Rico", "h_a": "a", "player_id": "2406", "situation": "FromCorner", "season": "2017", "shotType": "RightFoot", "match_id": "8043", "h_team": "Real Betis", "a_team": "Athletic Club", "h_goals": "0", "a_goals": "2", "date": "2017-12-22 18:30:00", "player_assisted": null, "lastAction": "BallTouch"}, {"id": "184441", "minute": "30", "result": "SavedShot", "X": "0.8780000305175781", "Y": "0.6580000305175782", "xG": "0.08034444600343704", "player": "Markel Susaeta", "h_a": "a", "player_id": "2405", "situation": "OpenPlay", "season": "2017", "shotType": "RightFoot", "match_id": "8043", "h_team": "Real Betis", "a_team": "Athletic Club", "h_goals": "0", "a_goals": "2", "date": "2017-12-22 18:30:00", "player_assisted": "I\u00f1aki Williams", "lastAction": "TakeOn"}, {"id": "184442", "minute": "30", "result": "BlockedShot", "X": "0.9390000152587891", "Y": "0.495", "xG": "0.6116679906845093", "player": "De Marcos", "h_a": "a", "player_id": "2452", "situation": "OpenPlay", "season": "2017", "shotType": "LeftFoot", "match_id": "8043", "h_team": "Real Betis", "a_team": "Athletic Club", "h_goals": "0", "a_goals": "2", "date": "2017-12-22 18:30:00", "player_assisted": null, "lastAction": "Rebound"}, {"id": "184443", "minute": "31", "result": "MissedShots", "X": "0.759000015258789", "Y": "0.3120000076293945", "xG": "0.012897728942334652", "player": "\u00cd\u00f1igo Lekue", "h_a": "a", "player_id": "2403", "situation": "FromCorner", "season": "2017", "shotType": "RightFoot", "match_id": "8043", "h_team": "Real Betis", "a_team": "Athletic Club", "h_goals": "0", "a_goals": "2", "date": "2017-12-22 18:30:00", "player_assisted": null, "lastAction": "Aerial"}, {"id": "184444", "minute": "33", "result": "SavedShot", "X": "0.89", "Y": "0.835", "xG": "0.06037832424044609", "player": "Markel Susaeta", "h_a": "a", "player_id": "2405", "situation": "DirectFreekick", "season": "2017", "shotType": "RightFoot", "match_id": "8043", "h_team": "Real Betis", "a_team": "Athletic Club", "h_goals": "0", "a_goals": "2", "date": "2017-12-22 18:30:00", "player_assisted": null, "lastAction": "Standard"}, {"id": "184445", "minute": "35", "result": "Goal", "X": "0.885", "Y": "0.5", "xG": "0.7432776093482971", "player": "Ra\u00fal Garc\u00eda", "h_a": "a", "player_id": "2400", "situation": "Penalty", "season": "2017", "shotType": "RightFoot", "match_id": "8043", "h_team": "Real Betis", "a_team": "Athletic Club", "h_goals": "0", "a_goals": "2", "date": "2017-12-22 18:30:00", "player_assisted": null, "lastAction": "Standard"}, {"id": "184447", "minute": "41", "result": "MissedShots", "X": "0.884000015258789", "Y": "0.5670000076293945", "xG": "0.08862525224685669", "player": "Ra\u00fal Garc\u00eda", "h_a": "a", "player_id": "2400", "situation": "OpenPlay", "season": "2017", "shotType": "RightFoot", "match_id": "8043", "h_team": "Real Betis", "a_team": "Athletic Club", "h_goals": "0", "a_goals": "2", "date": "2017-12-22 18:30:00", "player_assisted": "De Marcos", "lastAction": "Cross"}, {"id": "184449", "minute": "45", "result": "MissedShots", "X": "0.845999984741211", "Y": "0.415", "xG": "0.09653100371360779", "player": "I\u00f1aki Williams", "h_a": "a", "player_id": "2399", "situation": "OpenPlay", "season": "2017", "shotType": "RightFoot", "match_id": "8043", "h_team": "Real Betis", "a_team": "Athletic Club", "h_goals": "0", "a_goals": "2", "date": "2017-12-22 18:30:00", "player_assisted": "Ra\u00fal Garc\u00eda", "lastAction": "Pass"}, {"id": "184450", "minute": "46", "result": "MissedShots", "X": "0.8859999847412109", "Y": "0.46299999237060546", "xG": "0.09505832195281982", "player": "I\u00f1aki Williams", "h_a": "a", "player_id": "2399", "situation": "OpenPlay", "season": "2017", "shotType": "Head", "match_id": "8043", "h_team": "Real Betis", "a_team": "Athletic Club", "h_goals": "0", "a_goals": "2", "date": "2017-12-22 18:30:00", "player_assisted": "\u00cd\u00f1igo Lekue", "lastAction": "Cross"}, {"id": "184451", "minute": "50", "result": "MissedShots", "X": "0.8580000305175781", "Y": "0.3770000076293945", "xG": "0.08749688416719437", "player": "Markel Susaeta", "h_a": "a", "player_id": "2405", "situation": "OpenPlay", "season": "2017", "shotType": "RightFoot", "match_id": "8043", "h_team": "Real Betis", "a_team": "Athletic Club", "h_goals": "0", "a_goals": "2", "date": "2017-12-22 18:30:00", "player_assisted": "\u00cd\u00f1igo Lekue", "lastAction": "Pass"}, {"id": "184452", "minute": "50", "result": "SavedShot", "X": "0.874000015258789", "Y": "0.715", "xG": "0.05860139802098274", "player": "Ra\u00fal Garc\u00eda", "h_a": "a", "player_id": "2400", "situation": "OpenPlay", "season": "2017", "shotType": "RightFoot", "match_id": "8043", "h_team": "Real Betis", "a_team": "Athletic Club", "h_goals": "0", "a_goals": "2", "date": "2017-12-22 18:30:00", "player_assisted": "Iturraspe", "lastAction": "Chipped"}, {"id": "184453", "minute": "53", "result": "MissedShots", "X": "0.914000015258789", "Y": "0.49900001525878906", "xG": "0.10124756395816803", "player": "Unai N\u00fa\u00f1ez", "h_a": "a", "player_id": "6149", "situation": "FromCorner", "season": "2017", "shotType": "Head", "match_id": "8043", "h_team": "Real Betis", "a_team": "Athletic Club", "h_goals": "0", "a_goals": "2", "date": "2017-12-22 18:30:00", "player_assisted": "Markel Susaeta", "lastAction": "Cross"}, {"id": "184454", "minute": "54", "result": "BlockedShot", "X": "0.9330000305175781", "Y": "0.40299999237060546", "xG": "0.32174646854400635", "player": "Ra\u00fal Garc\u00eda", "h_a": "a", "player_id": "2400", "situation": "OpenPlay", "season": "2017", "shotType": "LeftFoot", "match_id": "8043", "h_team": "Real Betis", "a_team": "Athletic Club", "h_goals": "0", "a_goals": "2", "date": "2017-12-22 18:30:00", "player_assisted": "Markel Susaeta", "lastAction": "Chipped"}, {"id": "184455", "minute": "55", "result": "BlockedShot", "X": "0.875", "Y": "0.4209999847412109", "xG": "0.04912205785512924", "player": "I\u00f1aki Williams", "h_a": "a", "player_id": "2399", "situation": "OpenPlay", "season": "2017", "shotType": "RightFoot", "match_id": "8043", "h_team": "Real Betis", "a_team": "Athletic Club", "h_goals": "0", "a_goals": "2", "date": "2017-12-22 18:30:00", "player_assisted": null, "lastAction": "Aerial"}, {"id": "184457", "minute": "57", "result": "SavedShot", "X": "0.874000015258789", "Y": "0.6229999923706054", "xG": "0.05309393256902695", "player": "Ra\u00fal Garc\u00eda", "h_a": "a", "player_id": "2400", "situation": "OpenPlay", "season": "2017", "shotType": "RightFoot", "match_id": "8043", "h_team": "Real Betis", "a_team": "Athletic Club", "h_goals": "0", "a_goals": "2", "date": "2017-12-22 18:30:00", "player_assisted": "\u00cd\u00f1igo Lekue", "lastAction": "Cross"}, {"id": "184462", "minute": "75", "result": "MissedShots", "X": "0.894000015258789", "Y": "0.27600000381469725", "xG": "0.05248937010765076", "player": "Aduriz", "h_a": "a", "player_id": "2410", "situation": "OpenPlay", "season": "2017", "shotType": "RightFoot", "match_id": "8043", "h_team": "Real Betis", "a_team": "Athletic Club", "h_goals": "0", "a_goals": "2", "date": "2017-12-22 18:30:00", "player_assisted": null, "lastAction": "TakeOn"}, {"id": "184463", "minute": "76", "result": "SavedShot", "X": "0.8809999847412109", "Y": "0.5070000076293946", "xG": "0.4185105264186859", "player": "De Marcos", "h_a": "a", "player_id": "2452", "situation": "OpenPlay", "season": "2017", "shotType": "RightFoot", "match_id": "8043", "h_team": "Real Betis", "a_team": "Athletic Club", "h_goals": "0", "a_goals": "2", "date": "2017-12-22 18:30:00", "player_assisted": "Markel Susaeta", "lastAction": "Pass"}]}