{"h": [{"id": "14815", "minute": "3", "result": "MissedShots", "X": "0.805", "Y": "0.6519999694824219", "xG": "0.029940450564026833", "player": "Lee Cattermole", "h_a": "h", "player_id": "738", "situation": "OpenPlay", "season": "2014", "shotType": "RightFoot", "match_id": "4767", "h_team": "Sunderland", "a_team": "Manchester United", "h_goals": "1", "a_goals": "1", "date": "2014-08-24 16:00:00", "player_assisted": "Steven Fletcher", "lastAction": "Pass"}, {"id": "14817", "minute": "12", "result": "BlockedShot", "X": "0.8109999847412109", "Y": "0.4879999923706055", "xG": "0.0463314913213253", "player": "Lee Cattermole", "h_a": "h", "player_id": "738", "situation": "SetPiece", "season": "2014", "shotType": "RightFoot", "match_id": "4767", "h_team": "Sunderland", "a_team": "Manchester United", "h_goals": "1", "a_goals": "1", "date": "2014-08-24 16:00:00", "player_assisted": "Sebastian Larsson", "lastAction": "Pass"}, {"id": "14818", "minute": "15", "result": "SavedShot", "X": "0.8769999694824219", "Y": "0.6309999847412109", "xG": "0.08420415222644806", "player": "Connor Wickham", "h_a": "h", "player_id": "519", "situation": "OpenPlay", "season": "2014", "shotType": "LeftFoot", "match_id": "4767", "h_team": "Sunderland", "a_team": "Manchester United", "h_goals": "1", "a_goals": "1", "date": "2014-08-24 16:00:00", "player_assisted": "William Buckley", "lastAction": "Pass"}, {"id": "14820", "minute": "27", "result": "MissedShots", "X": "0.725", "Y": "0.62", "xG": "0.010530397295951843", "player": "Connor Wickham", "h_a": "h", "player_id": "519", "situation": "OpenPlay", "season": "2014", "shotType": "RightFoot", "match_id": "4767", "h_team": "Sunderland", "a_team": "Manchester United", "h_goals": "1", "a_goals": "1", "date": "2014-08-24 16:00:00", "player_assisted": "Patrick van Aanholt", "lastAction": "TakeOn"}, {"id": "14821", "minute": "29", "result": "Goal", "X": "0.93", "Y": "0.48700000762939455", "xG": "0.11746127158403397", "player": "Jack Rodwell", "h_a": "h", "player_id": "733", "situation": "FromCorner", "season": "2014", "shotType": "Head", "match_id": "4767", "h_team": "Sunderland", "a_team": "Manchester United", "h_goals": "1", "a_goals": "1", "date": "2014-08-24 16:00:00", "player_assisted": "Sebastian Larsson", "lastAction": "Cross"}, {"id": "14823", "minute": "41", "result": "MissedShots", "X": "0.91", "Y": "0.46599998474121096", "xG": "0.11064579337835312", "player": "Steven Fletcher", "h_a": "h", "player_id": "930", "situation": "OpenPlay", "season": "2014", "shotType": "LeftFoot", "match_id": "4767", "h_team": "Sunderland", "a_team": "Manchester United", "h_goals": "1", "a_goals": "1", "date": "2014-08-24 16:00:00", "player_assisted": "Jack Rodwell", "lastAction": "HeadPass"}, {"id": "14824", "minute": "50", "result": "MissedShots", "X": "0.909000015258789", "Y": "0.67", "xG": "0.07881546020507812", "player": "Connor Wickham", "h_a": "h", "player_id": "519", "situation": "OpenPlay", "season": "2014", "shotType": "RightFoot", "match_id": "4767", "h_team": "Sunderland", "a_team": "Manchester United", "h_goals": "1", "a_goals": "1", "date": "2014-08-24 16:00:00", "player_assisted": "William Buckley", "lastAction": "TakeOn"}, {"id": "14825", "minute": "65", "result": "MissedShots", "X": "0.89", "Y": "0.47200000762939454", "xG": "0.060331061482429504", "player": "Santiago Vergini", "h_a": "h", "player_id": "2192", "situation": "FromCorner", "season": "2014", "shotType": "RightFoot", "match_id": "4767", "h_team": "Sunderland", "a_team": "Manchester United", "h_goals": "1", "a_goals": "1", "date": "2014-08-24 16:00:00", "player_assisted": "Sebastian Larsson", "lastAction": "Cross"}, {"id": "14826", "minute": "67", "result": "BlockedShot", "X": "0.855", "Y": "0.285", "xG": "0.06145273149013519", "player": "Sebastian Larsson", "h_a": "h", "player_id": "740", "situation": "OpenPlay", "season": "2014", "shotType": "RightFoot", "match_id": "4767", "h_team": "Sunderland", "a_team": "Manchester United", "h_goals": "1", "a_goals": "1", "date": "2014-08-24 16:00:00", "player_assisted": "Connor Wickham", "lastAction": "Pass"}, {"id": "14829", "minute": "74", "result": "MissedShots", "X": "0.7569999694824219", "Y": "0.649000015258789", "xG": "0.05464737117290497", "player": "Sebastian Larsson", "h_a": "h", "player_id": "740", "situation": "DirectFreekick", "season": "2014", "shotType": "RightFoot", "match_id": "4767", "h_team": "Sunderland", "a_team": "Manchester United", "h_goals": "1", "a_goals": "1", "date": "2014-08-24 16:00:00", "player_assisted": null, "lastAction": "Standard"}, {"id": "14831", "minute": "81", "result": "SavedShot", "X": "0.735999984741211", "Y": "0.754000015258789", "xG": "0.012129110284149647", "player": "Patrick van Aanholt", "h_a": "h", "player_id": "730", "situation": "OpenPlay", "season": "2014", "shotType": "LeftFoot", "match_id": "4767", "h_team": "Sunderland", "a_team": "Manchester United", "h_goals": "1", "a_goals": "1", "date": "2014-08-24 16:00:00", "player_assisted": "Jozy Altidore", "lastAction": "Pass"}], "a": [{"id": "14816", "minute": "7", "result": "MissedShots", "X": "0.7630000305175781", "Y": "0.5220000076293946", "xG": "0.02534753456711769", "player": "Tom Cleverley", "h_a": "a", "player_id": "596", "situation": "OpenPlay", "season": "2014", "shotType": "RightFoot", "match_id": "4767", "h_team": "Sunderland", "a_team": "Manchester United", "h_goals": "1", "a_goals": "1", "date": "2014-08-24 16:00:00", "player_assisted": "Antonio Valencia", "lastAction": "Pass"}, {"id": "14819", "minute": "16", "result": "Goal", "X": "0.9690000152587891", "Y": "0.53", "xG": "0.6494782567024231", "player": "Juan Mata", "h_a": "a", "player_id": "554", "situation": "OpenPlay", "season": "2014", "shotType": "LeftFoot", "match_id": "4767", "h_team": "Sunderland", "a_team": "Manchester United", "h_goals": "1", "a_goals": "1", "date": "2014-08-24 16:00:00", "player_assisted": null, "lastAction": "None"}, {"id": "14822", "minute": "34", "result": "MissedShots", "X": "0.725999984741211", "Y": "0.6659999847412109", "xG": "0.03898036479949951", "player": "Wayne Rooney", "h_a": "a", "player_id": "629", "situation": "DirectFreekick", "season": "2014", "shotType": "RightFoot", "match_id": "4767", "h_team": "Sunderland", "a_team": "Manchester United", "h_goals": "1", "a_goals": "1", "date": "2014-08-24 16:00:00", "player_assisted": null, "lastAction": "Standard"}, {"id": "14827", "minute": "69", "result": "SavedShot", "X": "0.9230000305175782", "Y": "0.46599998474121096", "xG": "0.09967824071645737", "player": "Michael Keane", "h_a": "a", "player_id": "1653", "situation": "FromCorner", "season": "2014", "shotType": "Head", "match_id": "4767", "h_team": "Sunderland", "a_team": "Manchester United", "h_goals": "1", "a_goals": "1", "date": "2014-08-24 16:00:00", "player_assisted": "Juan Mata", "lastAction": "Cross"}, {"id": "14828", "minute": "71", "result": "BlockedShot", "X": "0.764000015258789", "Y": "0.3370000076293945", "xG": "0.02292673848569393", "player": "Wayne Rooney", "h_a": "a", "player_id": "629", "situation": "OpenPlay", "season": "2014", "shotType": "RightFoot", "match_id": "4767", "h_team": "Sunderland", "a_team": "Manchester United", "h_goals": "1", "a_goals": "1", "date": "2014-08-24 16:00:00", "player_assisted": "Adnan Januzaj", "lastAction": "Pass"}, {"id": "14830", "minute": "77", "result": "MissedShots", "X": "0.7609999847412109", "Y": "0.5540000152587891", "xG": "0.024093573912978172", "player": "Adnan Januzaj", "h_a": "a", "player_id": "323", "situation": "OpenPlay", "season": "2014", "shotType": "RightFoot", "match_id": "4767", "h_team": "Sunderland", "a_team": "Manchester United", "h_goals": "1", "a_goals": "1", "date": "2014-08-24 16:00:00", "player_assisted": "Tom Cleverley", "lastAction": "TakeOn"}, {"id": "14832", "minute": "86", "result": "BlockedShot", "X": "0.8640000152587891", "Y": "0.76", "xG": "0.024436060339212418", "player": "Ashley Young", "h_a": "a", "player_id": "631", "situation": "OpenPlay", "season": "2014", "shotType": "RightFoot", "match_id": "4767", "h_team": "Sunderland", "a_team": "Manchester United", "h_goals": "1", "a_goals": "1", "date": "2014-08-24 16:00:00", "player_assisted": null, "lastAction": "None"}, {"id": "14833", "minute": "88", "result": "SavedShot", "X": "0.774000015258789", "Y": "0.6669999694824219", "xG": "0.021454842761158943", "player": "Ashley Young", "h_a": "a", "player_id": "631", "situation": "OpenPlay", "season": "2014", "shotType": "RightFoot", "match_id": "4767", "h_team": "Sunderland", "a_team": "Manchester United", "h_goals": "1", "a_goals": "1", "date": "2014-08-24 16:00:00", "player_assisted": "Michael Keane", "lastAction": "Pass"}, {"id": "14834", "minute": "90", "result": "BlockedShot", "X": "0.7809999847412109", "Y": "0.7169999694824218", "xG": "0.015796085819602013", "player": "Adnan Januzaj", "h_a": "a", "player_id": "323", "situation": "OpenPlay", "season": "2014", "shotType": "LeftFoot", "match_id": "4767", "h_team": "Sunderland", "a_team": "Manchester United", "h_goals": "1", "a_goals": "1", "date": "2014-08-24 16:00:00", "player_assisted": null, "lastAction": "None"}, {"id": "14835", "minute": "93", "result": "MissedShots", "X": "0.745999984741211", "Y": "0.49900001525878906", "xG": "0.019365480169653893", "player": "Adnan Januzaj", "h_a": "a", "player_id": "323", "situation": "OpenPlay", "season": "2014", "shotType": "LeftFoot", "match_id": "4767", "h_team": "Sunderland", "a_team": "Manchester United", "h_goals": "1", "a_goals": "1", "date": "2014-08-24 16:00:00", "player_assisted": null, "lastAction": "None"}]}