{"h": [{"id": "70017", "minute": "0", "result": "MissedShots", "X": "0.71", "Y": "0.590999984741211", "xG": "0.013153409585356712", "player": "Adryan", "h_a": "h", "player_id": "3407", "situation": "OpenPlay", "season": "2015", "shotType": "RightFoot", "match_id": "2144", "h_team": "Nantes", "a_team": "Monaco", "h_goals": "0", "a_goals": "0", "date": "2016-02-28 17:00:00", "player_assisted": null, "lastAction": "Tackle"}, {"id": "70018", "minute": "4", "result": "SavedShot", "X": "0.9119999694824219", "Y": "0.315", "xG": "0.05446981266140938", "player": "Alejandro Bedoya", "h_a": "h", "player_id": "3405", "situation": "OpenPlay", "season": "2015", "shotType": "RightFoot", "match_id": "2144", "h_team": "Nantes", "a_team": "Monaco", "h_goals": "0", "a_goals": "0", "date": "2016-02-28 17:00:00", "player_assisted": null, "lastAction": "None"}, {"id": "70019", "minute": "4", "result": "MissedShots", "X": "0.8919999694824219", "Y": "0.5279999923706055", "xG": "0.04916497319936752", "player": "Oswaldo Vizcarrondo", "h_a": "h", "player_id": "3401", "situation": "FromCorner", "season": "2015", "shotType": "Head", "match_id": "2144", "h_team": "Nantes", "a_team": "Monaco", "h_goals": "0", "a_goals": "0", "date": "2016-02-28 17:00:00", "player_assisted": "Adryan", "lastAction": "Cross"}, {"id": "70020", "minute": "7", "result": "MissedShots", "X": "0.889000015258789", "Y": "0.7030000305175781", "xG": "0.052217982709407806", "player": "Emiliano Sala", "h_a": "h", "player_id": "3406", "situation": "OpenPlay", "season": "2015", "shotType": "RightFoot", "match_id": "2144", "h_team": "Nantes", "a_team": "Monaco", "h_goals": "0", "a_goals": "0", "date": "2016-02-28 17:00:00", "player_assisted": null, "lastAction": "Interception"}, {"id": "70021", "minute": "8", "result": "SavedShot", "X": "0.8830000305175781", "Y": "0.7240000152587891", "xG": "0.29640108346939087", "player": "Kolbeinn Sigthorsson", "h_a": "h", "player_id": "3408", "situation": "OpenPlay", "season": "2015", "shotType": "RightFoot", "match_id": "2144", "h_team": "Nantes", "a_team": "Monaco", "h_goals": "0", "a_goals": "0", "date": "2016-02-28 17:00:00", "player_assisted": "Guillaume Gillet", "lastAction": "Throughball"}, {"id": "70022", "minute": "11", "result": "BlockedShot", "X": "0.86", "Y": "0.5229999923706055", "xG": "0.024244749918580055", "player": "R\u00e9mi Gomis", "h_a": "h", "player_id": "3404", "situation": "OpenPlay", "season": "2015", "shotType": "Head", "match_id": "2144", "h_team": "Nantes", "a_team": "Monaco", "h_goals": "0", "a_goals": "0", "date": "2016-02-28 17:00:00", "player_assisted": "Alejandro Bedoya", "lastAction": "Cross"}, {"id": "70023", "minute": "15", "result": "SavedShot", "X": "0.8519999694824218", "Y": "0.37200000762939456", "xG": "0.06473424285650253", "player": "Kolbeinn Sigthorsson", "h_a": "h", "player_id": "3408", "situation": "OpenPlay", "season": "2015", "shotType": "RightFoot", "match_id": "2144", "h_team": "Nantes", "a_team": "Monaco", "h_goals": "0", "a_goals": "0", "date": "2016-02-28 17:00:00", "player_assisted": "Alejandro Bedoya", "lastAction": "Pass"}, {"id": "70024", "minute": "16", "result": "MissedShots", "X": "0.785", "Y": "0.5870000076293945", "xG": "0.03373740613460541", "player": "Lorik Cana", "h_a": "h", "player_id": "3400", "situation": "FromCorner", "season": "2015", "shotType": "LeftFoot", "match_id": "2144", "h_team": "Nantes", "a_team": "Monaco", "h_goals": "0", "a_goals": "0", "date": "2016-02-28 17:00:00", "player_assisted": "Guillaume Gillet", "lastAction": "Pass"}, {"id": "70026", "minute": "25", "result": "SavedShot", "X": "0.759000015258789", "Y": "0.45799999237060546", "xG": "0.025595450773835182", "player": "Emiliano Sala", "h_a": "h", "player_id": "3406", "situation": "OpenPlay", "season": "2015", "shotType": "RightFoot", "match_id": "2144", "h_team": "Nantes", "a_team": "Monaco", "h_goals": "0", "a_goals": "0", "date": "2016-02-28 17:00:00", "player_assisted": "Kolbeinn Sigthorsson", "lastAction": "BallTouch"}, {"id": "70028", "minute": "33", "result": "MissedShots", "X": "0.8969999694824219", "Y": "0.7519999694824219", "xG": "0.03002362884581089", "player": "Kolbeinn Sigthorsson", "h_a": "h", "player_id": "3408", "situation": "OpenPlay", "season": "2015", "shotType": "LeftFoot", "match_id": "2144", "h_team": "Nantes", "a_team": "Monaco", "h_goals": "0", "a_goals": "0", "date": "2016-02-28 17:00:00", "player_assisted": "Alejandro Bedoya", "lastAction": "Pass"}, {"id": "70031", "minute": "55", "result": "MissedShots", "X": "0.9159999847412109", "Y": "0.43200000762939456", "xG": "0.2423153817653656", "player": "R\u00e9mi Gomis", "h_a": "h", "player_id": "3404", "situation": "FromCorner", "season": "2015", "shotType": "Head", "match_id": "2144", "h_team": "Nantes", "a_team": "Monaco", "h_goals": "0", "a_goals": "0", "date": "2016-02-28 17:00:00", "player_assisted": "Lorik Cana", "lastAction": "HeadPass"}, {"id": "70032", "minute": "69", "result": "BlockedShot", "X": "0.71", "Y": "0.40099998474121096", "xG": "0.013157608918845654", "player": "Alejandro Bedoya", "h_a": "h", "player_id": "3405", "situation": "OpenPlay", "season": "2015", "shotType": "RightFoot", "match_id": "2144", "h_team": "Nantes", "a_team": "Monaco", "h_goals": "0", "a_goals": "0", "date": "2016-02-28 17:00:00", "player_assisted": "R\u00e9mi Gomis", "lastAction": "BallRecovery"}, {"id": "70033", "minute": "70", "result": "BlockedShot", "X": "0.7219999694824218", "Y": "0.44599998474121094", "xG": "0.04828223958611488", "player": "Kolbeinn Sigthorsson", "h_a": "h", "player_id": "3408", "situation": "DirectFreekick", "season": "2015", "shotType": "RightFoot", "match_id": "2144", "h_team": "Nantes", "a_team": "Monaco", "h_goals": "0", "a_goals": "0", "date": "2016-02-28 17:00:00", "player_assisted": null, "lastAction": "Standard"}, {"id": "70034", "minute": "76", "result": "MissedShots", "X": "0.9340000152587891", "Y": "0.47700000762939454", "xG": "0.4437735080718994", "player": "Emiliano Sala", "h_a": "h", "player_id": "3406", "situation": "OpenPlay", "season": "2015", "shotType": "Head", "match_id": "2144", "h_team": "Nantes", "a_team": "Monaco", "h_goals": "0", "a_goals": "0", "date": "2016-02-28 17:00:00", "player_assisted": "Guillaume Gillet", "lastAction": "Cross"}], "a": [{"id": "70025", "minute": "20", "result": "BlockedShot", "X": "0.725999984741211", "Y": "0.405", "xG": "0.017180679365992546", "player": "Kylian Mbappe-Lottin", "h_a": "a", "player_id": "3423", "situation": "OpenPlay", "season": "2015", "shotType": "RightFoot", "match_id": "2144", "h_team": "Nantes", "a_team": "Monaco", "h_goals": "0", "a_goals": "0", "date": "2016-02-28 17:00:00", "player_assisted": "Fabinho", "lastAction": "TakeOn"}, {"id": "70027", "minute": "29", "result": "MissedShots", "X": "0.74", "Y": "0.33599998474121096", "xG": "0.012086683884263039", "player": "Kylian Mbappe-Lottin", "h_a": "a", "player_id": "3423", "situation": "OpenPlay", "season": "2015", "shotType": "RightFoot", "match_id": "2144", "h_team": "Nantes", "a_team": "Monaco", "h_goals": "0", "a_goals": "0", "date": "2016-02-28 17:00:00", "player_assisted": null, "lastAction": "None"}, {"id": "70029", "minute": "34", "result": "BlockedShot", "X": "0.6959999847412109", "Y": "0.49700000762939456", "xG": "0.014180288650095463", "player": "Jo\u00e3o Moutinho", "h_a": "a", "player_id": "3422", "situation": "OpenPlay", "season": "2015", "shotType": "RightFoot", "match_id": "2144", "h_team": "Nantes", "a_team": "Monaco", "h_goals": "0", "a_goals": "0", "date": "2016-02-28 17:00:00", "player_assisted": "Thomas Lemar", "lastAction": "Pass"}, {"id": "70030", "minute": "49", "result": "SavedShot", "X": "0.860999984741211", "Y": "0.36200000762939455", "xG": "0.31435051560401917", "player": "Guido Carrillo", "h_a": "a", "player_id": "3424", "situation": "OpenPlay", "season": "2015", "shotType": "RightFoot", "match_id": "2144", "h_team": "Nantes", "a_team": "Monaco", "h_goals": "0", "a_goals": "0", "date": "2016-02-28 17:00:00", "player_assisted": null, "lastAction": "BallRecovery"}]}